quetzpy/__init__.py
quetzpy/extractor.py
quetzpy/params_manager.py
quetzpy/runner.py
quetzpy/modules/data_cleaning.py
quetzpy/modules/data_mining.py
quetzpy/modules/data_stats.py
quetzpy/modules/decorators.py
quetzpy/modules/twitter_connection.py
quetzpy-0.1.0.dist-info/LICENCE
quetzpy-0.1.0.dist-info/METADATA
quetzpy-0.1.0.dist-info/WHEEL
quetzpy-0.1.0.dist-info/top_level.txt
quetzpy-0.1.0.dist-info/RECORD
