Metadata-Version: 2.1
Name: quetzpy
Version: 0.1.0
Summary: Analyze how people are talking about any topic on Twitter.
Author-email: Kyllian Beguin <kyllian.beguin@gmail.com>
Classifier: Development Status :: 3 - Alpha
Classifier: License :: OSI Approved :: MIT License
Classifier: Natural Language :: English
Classifier: Operating System :: OS Independent
Classifier: Programming Language :: Python
Classifier: Programming Language :: Python :: 3.8
Classifier: Programming Language :: Python :: 3.9
Requires-Python: >=3.8
License-File: LICENCE
Requires-Dist: spacy (~=3.4)
Requires-Dist: spacymoji (~=3.0)
Requires-Dist: tweepy (~=4.12)
